params/__init__.py
params/params.py
params_py-0.4.1.dist-info/LICENSE
params_py-0.4.1.dist-info/METADATA
params_py-0.4.1.dist-info/WHEEL
params_py-0.4.1.dist-info/top_level.txt
params_py-0.4.1.dist-info/RECORD
