Metadata-Version: 2.1
Name: params-py
Version: 0.4.1
Summary: Command line flags alternative for Jupyter
Home-page: https://github.com/CourierKyn/params
Author: Franklin Li
Author-email: franklin_a_h_p@qq.com
License: MIT
Platform: UNKNOWN
Classifier: Programming Language :: Python
Classifier: Programming Language :: Python :: 2
Classifier: Programming Language :: Python :: 2.7
Classifier: Programming Language :: Python :: 3
Classifier: Programming Language :: Python :: 3.4
Classifier: Programming Language :: Python :: 3.5
Classifier: Programming Language :: Python :: 3.6
Classifier: Programming Language :: Python :: 3.7
Classifier: Programming Language :: Python :: 3.8
Classifier: Intended Audience :: Developers
Classifier: Topic :: Software Development :: Libraries :: Python Modules
Classifier: Operating System :: OS Independent
Requires-Dist: ipywidgets (~=7.5.1)
Requires-Dist: six (~=1.15.0)
Requires-Dist: enum34 ; python_version < "3.4"
